ufw_config/__init__.py
ufw_config/generator.py
ufw_config/ufw.py
ufw_config-0.0.4.dist-info/entry_points.txt
ufw_config-0.0.4.dist-info/LICENSE
ufw_config-0.0.4.dist-info/WHEEL
ufw_config-0.0.4.dist-info/METADATA
ufw_config-0.0.4.dist-info/RECORD
